cfdpost/__init__.py
cfdpost/cfdresult.py
cfdpost/data_format.py
cfdpost/section/PCA.py
cfdpost/section/__init__.py
cfdpost/section/physical.py
cfdpost-0.2.1.dist-info/LICENSE
cfdpost-0.2.1.dist-info/METADATA
cfdpost-0.2.1.dist-info/WHEEL
cfdpost-0.2.1.dist-info/top_level.txt
cfdpost-0.2.1.dist-info/RECORD
