Metadata-Version: 2.1
Name: cfdpost
Version: 0.2.1
Summary: This is the module of CFD post procedures
Home-page: UNKNOWN
Author: Runze LI
Author-email: swayli94@gmail.com
License: MIT
Download-URL: https://github.com/swayli94/cfdpost/
Keywords: CFD
Platform: UNKNOWN
Classifier: Programming Language :: Python :: 3
Requires-Dist: numpy
Requires-Dist: scipy
